[
    {
        "model": "match.student",
        "pk": 123,
        "fields": {
            "resume": "http://www.africau.edu/images/default/sample.pdf",
            "GPA": 3.99,
            "first_name": "Arami",
            "last_name": "Llera"
        }
    },
    {
        "model": "match.student",
        "pk": 246,
        "fields": {
            "resume": "http://www.africau.edu/images/default/sample2.pdf",
            "GPA": 3.74,
            "first_name": "lelia",
            "last_name": "Sanny"
        }
    },
    {
        "model": "match.company",
        "pk": 12,
        "fields": {
            "about_info": "The most amazing company",
            "company_location": "Plano, TX",
            "company_name": "JPMorgan Chase"
        }
    },
    {
        "model": "match.job",
        "pk": 10,
        "fields": {
            "description": "Amazing Job #1 is amazing because lalalala",
            "location": "Plano, TX",
            "compensation": 5000,
            "name": "Amazing Job #1",
            "number_of_positions": 1,
            "company": 12
        }
    },
    {
        "model": "match.job",
        "pk": 47,
        "fields": {
            "description": "Amazing Job #1 is amazing because lalalala",
            "location": "Plano, TX",
            "compensation": 5000,
            "name": "Zzzz boys",
            "number_of_positions": 1,
            "company": 12
        }
    },
    {
        "model": "match.job",
        "pk": 11,
        "fields": {
            "description": "Amazing Job #2 is amazing because lalalala",
            "location": "Plano, TX",
            "compensation": 5200,
            "name": "Amazing Job #2",
            "number_of_positions": 1,
            "company": 12
        }
    },
    {
        "model": "match.job",
        "pk": 12,
        "fields": {
            "description": "Amazing Job #3 is amazing because lalalala",
            "location": "Plano, TX",
            "compensation": 5400,
            "name": "Amazing Job #3",
            "number_of_positions": 1,
            "company": 12
        }
    },
    {
        "model": "match.job",
        "pk": 13,
        "fields": {
            "description": "Amazing Job #4 is amazing because lalalala",
            "location": "Plano, TX",
            "compensation": 5500,
            "name": "Amazing Job #4",
            "number_of_positions": 1,
            "company": 12
        }
    },
    {
        "model": "match.job",
        "pk": 14,
        "fields": {
            "description": "Amazing Job #5 is amazing because lalalala",
            "location": "Plano, TX",
            "compensation": 5600,
            "name": "Amazing Job #5",
            "number_of_positions": 1,
            "company": 12
        }
    },
    {
        "model": "match.job",
        "pk": 15,
        "fields": {
            "description": "Amazing Job #6 is amazing because lalalala",
            "location": "Plano, TX",
            "compensation": 5700,
            "name": "Amazing Job #6",
            "number_of_positions": 1,
            "company": 12
        }
    },
    {
        "model": "match.job",
        "pk": 16,
        "fields": {
            "description": "Amazing Job #7 is amazing because lalalala",
            "location": "Plano, TX",
            "compensation": 5800,
            "name": "Amazing Job #7",
            "number_of_positions": 1,
            "company": 12
        }
    },
    {
        "model": "match.job",
        "pk": 17,
        "fields": {
            "description": "Amazing Job #8 is amazing because lalalala",
            "location": "Sabrine, TX",
            "compensation": 5900,
            "name": "Amazing Job #8",
            "number_of_positions": 1,
            "company": 12
        }
    },
    {
        "model": "match.job",
        "pk": 18,
        "fields": {
            "description": "Amazing Job #9 is amazing because lalalala",
            "location": "Squirtle, TX",
            "compensation": 6800,
            "name": "Amazing Job #9",
            "number_of_positions": 1,
            "company": 12
        }
    },
    {
        "model": "match.job",
        "pk": 19,
        "fields": {
            "description": "Amazing Job #10 is amazing because lalalala",
            "location": "Antonio, TX",
            "compensation": 7000,
            "name": "Amazing Job #10",
            "number_of_positions": 1,
            "company": 12
        }
    },
    {
        "model": "match.StudentJob",
        "pk": 246,
        "fields": {
            "job": 19,
            "rank": 1,
            "student": 246
        }
    },
     {
        "model": "match.StudentJob",
        "pk": 123,
        "fields": {
            "job": 17,
            "rank": 1,
            "student": 123
        }
    },
    {
        "model": "match.CompanyStudent",
        "pk": 1,
        "fields": {
            "job": 47,
            "rank": 1,
            "student": 123
        }
    },
    {
        "model": "match.CompanyStudent",
        "pk": 23,
        "fields": {
            "job": 13,
            "rank": 2,
            "student": 246
        }
    }
]
